make.py
setup.py
sqlShort.py
sqlShort.egg-info/PKG-INFO
sqlShort.egg-info/SOURCES.txt
sqlShort.egg-info/dependency_links.txt
sqlShort.egg-info/top_level.txt