Metadata-Version: 1.1
Name: sqlShort
Version: 0.3
Summary: A tiny wrapper for the Python modules MySQLdb and Sqlite
Home-page: http://code.google.com/p/sqlshort/
Author: Etienne Gaudrain
Author-email: egaudrain@gmail.com
License: GNU GPL 3
Platform: UNKNOWN
Requires: numpy
Provides: sqlShort
